README.rst
setup.py
sqlalchemy_graphql/__init__.py
sqlalchemy_graphql.egg-info/PKG-INFO
sqlalchemy_graphql.egg-info/SOURCES.txt
sqlalchemy_graphql.egg-info/dependency_links.txt
sqlalchemy_graphql.egg-info/not-zip-safe
sqlalchemy_graphql.egg-info/requires.txt
sqlalchemy_graphql.egg-info/top_level.txt
sqlalchemy_graphql/epoxy/__init__.py
sqlalchemy_graphql/epoxy/custom_scalar_types.py
sqlalchemy_graphql/epoxy/query.py
sqlalchemy_graphql/epoxy/utils.py