Metadata-Version: 1.0
Name: sqlalchemy-graphql
Version: 1.3
Summary: GraphQL extension for dealing with SQLAlchemy
Home-page: UNKNOWN
Author: Adriel Velazquez
Author-email: adrielvelazquez@gmail.com
License: UNKNOWN
Platform: UNKNOWN
